boolrule/__init__.py
boolrule/boolrule.py
boolrule/py.typed
boolrule-0.3.5.dist-info/AUTHORS.rst
boolrule-0.3.5.dist-info/LICENSE
boolrule-0.3.5.dist-info/METADATA
boolrule-0.3.5.dist-info/WHEEL
boolrule-0.3.5.dist-info/top_level.txt
boolrule-0.3.5.dist-info/RECORD
