Metadata-Version: 2.1
Name: boolrule
Version: 0.3.5
Summary: Simple boolean expression evaluation engine
Home-page: https://github.com/tailsdotcom/boolrule
Author: Steve Webster
Author-email: spjwebster@gmail.com
License: MIT license
Keywords: boolrule boolean expression
Classifier: Development Status :: 4 - Beta
Classifier: Intended Audience :: Developers
Classifier: License :: OSI Approved :: MIT License
Classifier: Natural Language :: English
Classifier: Programming Language :: Python :: 2
Classifier: Programming Language :: Python :: 2.7
Classifier: Programming Language :: Python :: 3
Classifier: Programming Language :: Python :: 3.6
Classifier: Programming Language :: Python :: 3.7
Classifier: Programming Language :: Python :: 3.8
Classifier: Topic :: Text Processing :: General
License-File: LICENSE
License-File: AUTHORS.rst
Requires-Dist: pyparsing
